PyR3/__init__.py
PyR3/install_bpy.py
PyR3/mp_cli.py
PyR3/construct/__init__.py
PyR3/construct/__main__.py
PyR3/construct/mp.py
PyR3/construct/parse_place.py
PyR3/construct/cli/__init__.py
PyR3/construct/cli/add.py
PyR3/construct/cli/check.py
PyR3/construct/cli/const.py
PyR3/construct/cli/from_place.py
PyR3/construct/cli/new.py
PyR3/contrib/__init__.py
PyR3/contrib/factories/CapacitorCase.py
PyR3/contrib/factories/__init__.py
PyR3/factory/MeshFactory.py
PyR3/factory/__init__.py
PyR3/factory/fields/Field.py
PyR3/factory/fields/Number.py
PyR3/factory/fields/Select.py
PyR3/factory/fields/String.py
PyR3/factory/fields/Struct.py
PyR3/factory/fields/Unit.py
PyR3/factory/fields/__init__.py
PyR3/meshlib/__init__.py
PyR3/meshlib/__main__.py
PyR3/meshlib/cli/__init__.py
PyR3/meshlib/cli/add.py
PyR3/meshlib/cli/const.py
PyR3/meshlib/cli/mklib.py
PyR3/meshlib/lib_obj/__init__.py
PyR3/meshlib/lib_obj/lib_info.py
PyR3/meshlib/lib_obj/model_info.py
PyR3/meshlib/lib_obj/usertags.py
PyR3/shortcut/__init__.py
PyR3/shortcut/context.py
PyR3/shortcut/edit.py
PyR3/shortcut/io.py
PyR3/shortcut/material.py
PyR3/shortcut/mesh.py
PyR3/shortcut/modifiers.py
PyR3/shortcut/transform.py
PyR3-0.3.0.dist-info/AUTHORS.rst
PyR3-0.3.0.dist-info/LICENSE
PyR3-0.3.0.dist-info/METADATA
PyR3-0.3.0.dist-info/WHEEL
PyR3-0.3.0.dist-info/entry_points.txt
PyR3-0.3.0.dist-info/top_level.txt
PyR3-0.3.0.dist-info/RECORD
