Metadata-Version: 2.1
Name: PyR3
Version: 0.3.0
Summary: A set of tools extending the capabilities of bpy (blender as a python module).
Home-page: https://github.com/Argmaster/PyR3
Author: Krzysztof Wiśniewski
Author-email: argmaster.world@gmail.com
License: MIT
Project-URL: Documentation, https://PyR3.readthedocs.io/
Project-URL: Changelog, https://PyR3.readthedocs.io/en/latest/changelog.html
Project-URL: Issue Tracker, https://github.com/Argmaster/PyR3/issues
Keywords: python-3,python-3.9
Platform: UNKNOWN
Classifier: Development Status :: 4 - Beta
Classifier: Intended Audience :: Developers
Classifier: License :: OSI Approved :: MIT License
Classifier: Operating System :: Unix
Classifier: Operating System :: POSIX
Classifier: Operating System :: Microsoft :: Windows
Classifier: Programming Language :: Python
Classifier: Programming Language :: Python :: 3
Classifier: Programming Language :: Python :: 3 :: Only
Classifier: Programming Language :: Python :: 3.9
Classifier: Programming Language :: Python :: Implementation :: CPython
Classifier: Topic :: Multimedia :: Graphics :: 3D Rendering
Classifier: Topic :: Text Processing :: General
Classifier: Topic :: Utilities
Requires-Python: ==3.9.*
Requires-Dist: numpy (>=1.21.0)
Requires-Dist: requests (>=2.26.0)
Requires-Dist: pyYAML (>=6.0)
Requires-Dist: packaging (>=21.0)
Requires-Dist: pydantic (>=1.8.2)
Requires-Dist: rich (>=10.12.0)
Requires-Dist: click (>=8.0.3)
